rk/__init__.py
rk_rubykit-0.1.0.dist-info/licenses/LICENSE
rk_rubykit-0.1.0.dist-info/METADATA
rk_rubykit-0.1.0.dist-info/WHEEL
rk_rubykit-0.1.0.dist-info/entry_points.txt
rk_rubykit-0.1.0.dist-info/top_level.txt
rk_rubykit-0.1.0.dist-info/RECORD
