Metadata-Version: 2.4
Name: RK.rubyKit
Version: 0.1.0
Summary: Python library for developing apps for RubyOS
Home-page: https://github.com/rubykit/rk.rubykit
Author: RubyKit Team
Author-email: RubyKit Team <contact@rubykit.dev>
License: MIT
Project-URL: Homepage, https://github.com/rubykit/rk.rubykit
Project-URL: Documentation, https://github.com/rubykit/rk.rubykit#readme
Project-URL: Repository, https://github.com/rubykit/rk.rubykit
Project-URL: Bug Tracker, https://github.com/rubykit/rk.rubykit/issues
Classifier: Development Status :: 3 - Alpha
Classifier: Intended Audience :: Developers
Classifier: Topic :: Software Development :: Libraries :: Application Frameworks
Classifier: License :: OSI Approved :: MIT License
Classifier: Programming Language :: Python :: 3
Classifier: Programming Language :: Python :: 3.8
Classifier: Programming Language :: Python :: 3.9
Classifier: Programming Language :: Python :: 3.10
Classifier: Programming Language :: Python :: 3.11
Classifier: Programming Language :: Python :: 3.12
Requires-Python: >=3.8
License-File: LICENSE
Dynamic: author
Dynamic: home-page
Dynamic: license-file
Dynamic: requires-python
